{"file":"cc_sheet_match_c.png","frames":{
"cc_match_btn_exit_n":{"x":478,"y":435,"w":140,"h":75,"offX":0,"offY":0,"sourceW":140,"sourceH":75},
"cc_match_btn_exit_txt_h":{"x":1924,"y":340,"w":101,"h":30,"offX":0,"offY":0,"sourceW":101,"sourceH":30},
"cc_match_btn_exit_txt_n":{"x":1924,"y":372,"w":101,"h":30,"offX":0,"offY":0,"sourceW":101,"sourceH":30},
"cc_match_btn_help_h":{"x":620,"y":435,"w":154,"h":67,"offX":0,"offY":0,"sourceW":154,"sourceH":67},
"cc_match_btn_help_n":{"x":1086,"y":441,"w":154,"h":67,"offX":0,"offY":0,"sourceW":154,"sourceH":67},
"cc_match_btn_reward_h":{"x":998,"y":239,"w":154,"h":75,"offX":0,"offY":0,"sourceW":154,"sourceH":75},
"cc_match_btn_reward_n":{"x":998,"y":162,"w":154,"h":75,"offX":0,"offY":0,"sourceW":154,"sourceH":75},
"cc_match_btn_sign_up_h":{"x":802,"y":386,"w":140,"h":75,"offX":0,"offY":0,"sourceW":140,"sourceH":75},
"cc_match_btn_sign_up_n":{"x":1782,"y":340,"w":140,"h":75,"offX":0,"offY":0,"sourceW":140,"sourceH":75},
"cc_match_finish_bg":{"x":1189,"y":0,"w":353,"h":439,"offX":0,"offY":0,"sourceW":353,"sourceH":439},
"cc_match_finish_top":{"x":650,"y":162,"w":346,"h":177,"offX":0,"offY":0,"sourceW":346,"sourceH":177},
"cc_match_float_bg":{"x":0,"y":0,"w":1187,"h":160,"offX":0,"offY":0,"sourceW":1187,"sourceH":160},
"cc_match_getreward_h":{"x":998,"y":316,"w":140,"h":75,"offX":0,"offY":0,"sourceW":140,"sourceH":75},
"cc_match_getreward_n":{"x":1782,"y":417,"w":140,"h":75,"offX":0,"offY":0,"sourceW":140,"sourceH":75},
"cc_match_panel_bg":{"x":0,"y":162,"w":648,"h":164,"offX":0,"offY":0,"sourceW":648,"sourceH":164},
"cc_match_panel_bg_2":{"x":1544,"y":0,"w":442,"h":338,"offX":0,"offY":0,"sourceW":442,"sourceH":338},
"cc_match_rank_detail":{"x":0,"y":447,"w":189,"h":35,"offX":1,"offY":2,"sourceW":191,"sourceH":38},
"cc_match_word_4":{"x":0,"y":328,"w":237,"h":117,"offX":0,"offY":0,"sourceW":237,"sourceH":117},
"cc_match_word_5":{"x":1544,"y":340,"w":236,"h":117,"offX":0,"offY":0,"sourceW":236,"sourceH":117},
"cc_match_word_6":{"x":239,"y":328,"w":237,"h":117,"offX":0,"offY":0,"sourceW":237,"sourceH":117},
"cc_match_word_17":{"x":1988,"y":0,"w":41,"h":37,"offX":0,"offY":0,"sourceW":41,"sourceH":37},
"cc_match_word_18":{"x":1924,"y":404,"w":84,"h":35,"offX":0,"offY":0,"sourceW":84,"sourceH":35},
"cc_match_word_19":{"x":1086,"y":393,"w":84,"h":35,"offX":0,"offY":0,"sourceW":84,"sourceH":35},
"cc_match_word_20":{"x":478,"y":386,"w":322,"h":47,"offX":0,"offY":0,"sourceW":322,"sourceH":47},
"cc_match_word_21":{"x":478,"y":341,"w":442,"h":43,"offX":0,"offY":0,"sourceW":442,"sourceH":43},
"cc_match_word_22":{"x":1242,"y":441,"w":139,"h":51,"offX":0,"offY":0,"sourceW":139,"sourceH":51},
"cc_match_word_24":{"x":1383,"y":441,"w":130,"h":37,"offX":0,"offY":0,"sourceW":130,"sourceH":37},
"cc_match_word_26":{"x":1924,"y":441,"w":60,"h":29,"offX":0,"offY":0,"sourceW":60,"sourceH":29},
"cc_match_word_29":{"x":922,"y":341,"w":68,"h":36,"offX":0,"offY":0,"sourceW":68,"sourceH":36},
"cc_match_btn_exit_h":{"x":944,"y":393,"w":140,"h":75,"offX":0,"offY":0,"sourceW":140,"sourceH":75}}}