{"mc":{
	"browTortise":{
		"frameRate":24,
		"labels":[
			{"name":"normal","frame":1,"end":53}
			
			],
		"events":[
			
			],
		"frames":[
			
			{
			"res":"560002",
			"x":33,
			"y":20
			},
			{
			"res":"560003",
			"x":30,
			"y":17
			},
			{
			"res":"560004",
			"x":27,
			"y":14
			},
			{
			"res":"560005",
			"x":23,
			"y":11
			},
			{
			"res":"560006",
			"x":20,
			"y":7
			},
			{
			"res":"560007",
			"x":17,
			"y":4
			},
			{
			"res":"560008",
			"x":17,
			"y":4
			},
			{
			"res":"560009",
			"x":17,
			"y":4
			},
			{
			"res":"560010",
			"x":14,
			"y":1
			},
			{
			"res":"560011",
			"x":15,
			"y":2
			},
			{
			"res":"560012",
			"x":16,
			"y":3
			},
			{
			"res":"560013",
			"x":17,
			"y":4
			},
			{
			"res":"560014",
			"x":17,
			"y":4
			},
			{
			"res":"560015",
			"x":17,
			"y":4
			},
			{
			"res":"560016",
			"x":17,
			"y":4
			},
			{
			"res":"560017",
			"x":17,
			"y":4
			},
			{
			"res":"560018",
			"x":17,
			"y":4
			},
			{
			"res":"560019",
			"x":17,
			"y":4
			},
			{
			"res":"560020",
			"x":17,
			"y":4
			},
			{
			"res":"560021",
			"x":17,
			"y":4
			},
			{
			"res":"560022",
			"x":17,
			"y":4
			},
			{
			"res":"560023",
			"x":17,
			"y":4
			},
			{
			"res":"560024",
			"x":2,
			"y":4
			},
			{
			"res":"560025",
			"x":3,
			"y":4
			},
			{
			"res":"560026",
			"x":3,
			"y":4
			},
			{
			"res":"560027",
			"x":4,
			"y":4
			},
			{
			"res":"560028",
			"x":5,
			"y":4
			},
			{
			"res":"560029",
			"x":5,
			"y":4
			},
			{
			"res":"560030",
			"x":6,
			"y":4
			},
			{
			"res":"560031",
			"x":7,
			"y":4
			},
			{
			"res":"560032",
			"x":7,
			"y":4
			},
			{
			"res":"560033",
			"x":8,
			"y":4
			},
			{
			"res":"560034",
			"x":9,
			"y":4
			},
			{
			"res":"560035",
			"x":9,
			"y":4
			},
			{
			"res":"560036",
			"x":10,
			"y":4
			},
			{
			"res":"560037",
			"x":11,
			"y":4
			},
			{
			"res":"560038",
			"x":11,
			"y":4
			},
			{
			"res":"560039",
			"x":12,
			"y":4
			},
			{
			"res":"560040",
			"x":13,
			"y":4
			},
			{
			"res":"560041",
			"x":13,
			"y":4
			},
			{
			"res":"560042",
			"x":14,
			"y":4
			},
			{
			"res":"560043",
			"x":15,
			"y":4
			},
			{
			"res":"560044",
			"x":16,
			"y":4
			},
			{
			"res":"560045",
			"x":16,
			"y":4
			},
			{
			"res":"560046",
			"x":17,
			"y":4
			},
			{
			"res":"560047",
			"x":17,
			"y":4
			},
			{
			"res":"560048",
			"x":17,
			"y":4
			},
			{
			"res":"560049",
			"x":17,
			"y":4
			},
			{
			"res":"560050",
			"x":17,
			"y":4
			},
			{
			"res":"560051",
			"x":17,
			"y":4
			},
			{
			"res":"560052",
			"x":17,
			"y":4
			},
			{
			"res":"560053",
			"x":17,
			"y":4
			},
			{
			"res":"560054",
			"x":17,
			"y":4
			}
			]
}},
	"res":{
		"560002":{"x":472,"y":91,"w":14,"h":14},
		"560003":{"x":484,"y":29,"w":20,"h":21},
		"560004":{"x":484,"y":0,"w":27,"h":28},
		"560005":{"x":472,"y":55,"w":33,"h":34},
		"560006":{"x":467,"y":110,"w":40,"h":41},
		"560007":{"x":0,"y":269,"w":47,"h":48},
		"560008":{"x":0,"y":269,"w":47,"h":48},
		"560009":{"x":0,"y":269,"w":47,"h":48},
		"560010":{"x":132,"y":273,"w":52,"h":54},
		"560011":{"x":0,"y":165,"w":50,"h":52},
		"560012":{"x":0,"y":218,"w":48,"h":50},
		"560013":{"x":0,"y":269,"w":47,"h":48},
		"560014":{"x":0,"y":269,"w":47,"h":48},
		"560015":{"x":0,"y":269,"w":47,"h":48},
		"560016":{"x":0,"y":269,"w":47,"h":48},
		"560017":{"x":0,"y":269,"w":47,"h":48},
		"560018":{"x":0,"y":269,"w":47,"h":48},
		"560019":{"x":0,"y":269,"w":47,"h":48},
		"560020":{"x":0,"y":269,"w":47,"h":48},
		"560021":{"x":0,"y":269,"w":47,"h":48},
		"560022":{"x":0,"y":269,"w":47,"h":48},
		"560023":{"x":0,"y":269,"w":47,"h":48},
		"560024":{"x":132,"y":219,"w":63,"h":53},
		"560025":{"x":198,"y":271,"w":63,"h":53},
		"560026":{"x":202,"y":163,"w":64,"h":54},
		"560027":{"x":406,"y":55,"w":64,"h":54},
		"560028":{"x":270,"y":110,"w":64,"h":54},
		"560029":{"x":209,"y":54,"w":65,"h":54},
		"560030":{"x":66,"y":110,"w":65,"h":54},
		"560031":{"x":136,"y":109,"w":65,"h":54},
		"560032":{"x":275,"y":55,"w":65,"h":54},
		"560033":{"x":132,"y":164,"w":64,"h":54},
		"560034":{"x":0,"y":55,"w":65,"h":54},
		"560035":{"x":418,"y":0,"w":65,"h":54},
		"560036":{"x":341,"y":55,"w":64,"h":54},
		"560037":{"x":70,"y":55,"w":65,"h":54},
		"560038":{"x":352,"y":0,"w":65,"h":54},
		"560039":{"x":0,"y":110,"w":64,"h":54},
		"560040":{"x":268,"y":165,"w":65,"h":52},
		"560041":{"x":268,"y":219,"w":65,"h":52},
		"560042":{"x":335,"y":110,"w":65,"h":52},
		"560043":{"x":66,"y":218,"w":65,"h":52},
		"560044":{"x":198,"y":218,"w":64,"h":52},
		"560045":{"x":335,"y":164,"w":65,"h":52},
		"560046":{"x":401,"y":110,"w":65,"h":52},
		"560047":{"x":66,"y":165,"w":65,"h":52},
		"560048":{"x":202,"y":109,"w":66,"h":52},
		"560049":{"x":141,"y":54,"w":67,"h":54},
		"560050":{"x":283,"y":0,"w":68,"h":54},
		"560051":{"x":0,"y":0,"w":69,"h":54},
		"560052":{"x":70,"y":0,"w":69,"h":53},
		"560053":{"x":141,"y":0,"w":70,"h":53},
		"560054":{"x":212,"y":0,"w":70,"h":53}
	}}