{"file":"sheet_play_c.png","frames":{
"play_36":{"x":1277,"y":355,"w":119,"h":71,"offX":0,"offY":0,"sourceW":119,"sourceH":71},
"play_animate_gold_light":{"x":1478,"y":163,"w":300,"h":80,"offX":0,"offY":0,"sourceW":300,"sourceH":80},
"play_animate_star":{"x":288,"y":0,"w":239,"h":239,"offX":9,"offY":9,"sourceW":256,"sourceH":256},
"play_bg_1":{"x":1892,"y":290,"w":115,"h":126,"offX":0,"offY":0,"sourceW":115,"sourceH":126},
"play_bg_2":{"x":288,"y":241,"w":145,"h":126,"offX":0,"offY":0,"sourceW":145,"sourceH":126},
"play_bg_3":{"x":1813,"y":0,"w":163,"h":171,"offX":0,"offY":0,"sourceW":163,"sourceH":171},
"play_bg_4":{"x":1780,"y":173,"w":249,"h":75,"offX":0,"offY":0,"sourceW":249,"sourceH":75},
"play_bg_5":{"x":1528,"y":0,"w":283,"h":161,"offX":0,"offY":0,"sourceW":283,"sourceH":161},
"play_bottom_star":{"x":938,"y":115,"w":19,"h":19,"offX":0,"offY":0,"sourceW":19,"sourceH":19},
"play_btn_13_h":{"x":914,"y":259,"w":161,"h":94,"offX":0,"offY":0,"sourceW":161,"sourceH":94},
"play_btn_13_n":{"x":721,"y":298,"w":161,"h":94,"offX":0,"offY":0,"sourceW":161,"sourceH":94},
"play_btn_back_h":{"x":710,"y":394,"w":75,"h":74,"offX":0,"offY":0,"sourceW":75,"sourceH":74},
"play_btn_back_n":{"x":77,"y":388,"w":75,"h":74,"offX":0,"offY":0,"sourceW":75,"sourceH":74},
"play_btn_blue_h":{"x":1729,"y":290,"w":161,"h":94,"offX":0,"offY":0,"sourceW":161,"sourceH":94},
"play_btn_blue_n":{"x":1566,"y":290,"w":161,"h":94,"offX":0,"offY":0,"sourceW":161,"sourceH":94},
"play_btn_d":{"x":1403,"y":290,"w":161,"h":94,"offX":0,"offY":0,"sourceW":161,"sourceH":94},
"play_btn_orange_h":{"x":1240,"y":259,"w":161,"h":94,"offX":0,"offY":0,"sourceW":161,"sourceH":94},
"play_btn_orange_n":{"x":1077,"y":259,"w":161,"h":94,"offX":0,"offY":0,"sourceW":161,"sourceH":94},
"play_btn_record_h":{"x":0,"y":388,"w":75,"h":74,"offX":0,"offY":0,"sourceW":76,"sourceH":75},
"play_btn_record_n":{"x":1744,"y":386,"w":75,"h":74,"offX":0,"offY":0,"sourceW":76,"sourceH":75},
"play_btn_set_h":{"x":941,"y":399,"w":75,"h":74,"offX":0,"offY":0,"sourceW":75,"sourceH":74},
"play_btn_set_n":{"x":864,"y":399,"w":75,"h":74,"offX":0,"offY":0,"sourceW":75,"sourceH":74},
"play_btn_trusteeship_d":{"x":229,"y":415,"w":73,"h":72,"offX":1,"offY":1,"sourceW":75,"sourceH":74},
"play_btn_trusteeship_h":{"x":154,"y":415,"w":73,"h":72,"offX":1,"offY":1,"sourceW":75,"sourceH":74},
"play_btn_trusteeship_n":{"x":1448,"y":85,"w":73,"h":72,"offX":1,"offY":1,"sourceW":75,"sourceH":74},
"play_btn_word_1_d":{"x":1542,"y":522,"w":75,"h":50,"offX":44,"offY":17,"sourceW":161,"sourceH":94},
"play_btn_word_1_h":{"x":721,"y":522,"w":75,"h":50,"offX":44,"offY":17,"sourceW":161,"sourceH":94},
"play_btn_word_1_n":{"x":644,"y":522,"w":75,"h":50,"offX":44,"offY":17,"sourceW":161,"sourceH":94},
"play_btn_word_2_d":{"x":1964,"y":472,"w":81,"h":50,"offX":41,"offY":17,"sourceW":161,"sourceH":94},
"play_btn_word_2_h":{"x":265,"y":494,"w":81,"h":50,"offX":41,"offY":17,"sourceW":161,"sourceH":94},
"play_btn_word_2_n":{"x":182,"y":489,"w":81,"h":50,"offX":41,"offY":17,"sourceW":161,"sourceH":94},
"play_btn_word_3_h":{"x":99,"y":489,"w":81,"h":50,"offX":41,"offY":17,"sourceW":161,"sourceH":94},
"play_btn_word_3_n":{"x":1459,"y":484,"w":81,"h":50,"offX":41,"offY":17,"sourceW":161,"sourceH":94},
"play_btn_word_again_d":{"x":504,"y":459,"w":98,"h":50,"offX":32,"offY":17,"sourceW":161,"sourceH":94},
"play_btn_word_again_h":{"x":1018,"y":454,"w":98,"h":50,"offX":32,"offY":17,"sourceW":161,"sourceH":94},
"play_btn_word_again_n":{"x":1122,"y":451,"w":98,"h":50,"offX":32,"offY":17,"sourceW":161,"sourceH":94},
"play_btn_word_come_d":{"x":404,"y":442,"w":98,"h":50,"offX":32,"offY":17,"sourceW":161,"sourceH":94},
"play_btn_word_come_h":{"x":304,"y":442,"w":98,"h":50,"offX":32,"offY":17,"sourceW":161,"sourceH":94},
"play_btn_word_come_n":{"x":1470,"y":432,"w":98,"h":50,"offX":32,"offY":17,"sourceW":161,"sourceH":94},
"play_btn_word_continue_h":{"x":356,"y":379,"w":100,"h":61,"offX":22,"offY":7,"sourceW":140,"sourceH":75},
"play_btn_word_continue_n":{"x":458,"y":379,"w":100,"h":61,"offX":22,"offY":7,"sourceW":140,"sourceH":75},
"play_btn_word_exchange_h":{"x":703,"y":470,"w":97,"h":50,"offX":32,"offY":17,"sourceW":161,"sourceH":94},
"play_btn_word_exchange_n":{"x":0,"y":464,"w":97,"h":50,"offX":32,"offY":17,"sourceW":161,"sourceH":94},
"play_btn_word_getready_h":{"x":1921,"y":418,"w":98,"h":52,"offX":32,"offY":16,"sourceW":161,"sourceH":94},
"play_btn_word_getready_n":{"x":1821,"y":418,"w":98,"h":52,"offX":32,"offY":16,"sourceW":161,"sourceH":94},
"play_btn_word_no_d":{"x":1570,"y":470,"w":97,"h":50,"offX":33,"offY":16,"sourceW":161,"sourceH":94},
"play_btn_word_no_h":{"x":604,"y":459,"w":97,"h":50,"offX":33,"offY":16,"sourceW":161,"sourceH":94},
"play_btn_word_no_n":{"x":1669,"y":470,"w":97,"h":50,"offX":33,"offY":16,"sourceW":161,"sourceH":94},
"play_btn_word_nocall_h":{"x":1768,"y":472,"w":96,"h":50,"offX":34,"offY":17,"sourceW":161,"sourceH":94},
"play_btn_word_nocall_n":{"x":1866,"y":472,"w":96,"h":50,"offX":34,"offY":17,"sourceW":161,"sourceH":94},
"play_btn_word_prompt_d":{"x":802,"y":475,"w":97,"h":49,"offX":32,"offY":18,"sourceW":161,"sourceH":94},
"play_btn_word_prompt_h":{"x":1222,"y":481,"w":97,"h":49,"offX":33,"offY":19,"sourceW":161,"sourceH":94},
"play_btn_word_prompt_n":{"x":901,"y":475,"w":97,"h":49,"offX":33,"offY":19,"sourceW":161,"sourceH":94},
"play_btn_word_start":{"x":1277,"y":428,"w":97,"h":51,"offX":1,"offY":1,"sourceW":100,"sourceH":53},
"play_cancel_trust_c":{"x":938,"y":159,"w":268,"h":98,"offX":0,"offY":6,"sourceW":268,"sourceH":117},
"play_cancel_trust_n":{"x":1208,"y":159,"w":268,"h":98,"offX":0,"offY":6,"sourceW":268,"sourceH":117},
"play_card_count_bg":{"x":1978,"y":109,"w":45,"h":52,"offX":0,"offY":0,"sourceW":45,"sourceH":52},
"play_cardshadow":{"x":1978,"y":0,"w":64,"h":52,"offX":0,"offY":0,"sourceW":64,"sourceH":52},
"play_hand_ok":{"x":1398,"y":386,"w":70,"h":83,"offX":0,"offY":0,"sourceW":70,"sourceH":83},
"play_master_card_bg":{"x":529,"y":0,"w":435,"h":113,"offX":0,"offY":0,"sourceW":435,"sourceH":113},
"play_match_detail_bg":{"x":884,"y":355,"w":276,"h":42,"offX":0,"offY":0,"sourceW":276,"sourceH":42},
"play_match_place_info_bg":{"x":1601,"y":427,"w":123,"h":41,"offX":0,"offY":0,"sourceW":123,"sourceH":41},
"play_name_bg":{"x":1950,"y":250,"w":91,"h":22,"offX":0,"offY":0,"sourceW":91,"sourceH":22},
"play_offline":{"x":1162,"y":355,"w":113,"h":94,"offX":0,"offY":0,"sourceW":113,"sourceH":94},
"play_personal_info_bg":{"x":1478,"y":250,"w":470,"h":38,"offX":0,"offY":0,"sourceW":470,"sourceH":38},
"play_record_bg":{"x":966,"y":85,"w":480,"h":72,"offX":0,"offY":0,"sourceW":480,"sourceH":72},
"play_recorder_gift":{"x":435,"y":299,"w":180,"h":78,"offX":4,"offY":0,"sourceW":190,"sourceH":82},
"play_recorder_outofdate":{"x":0,"y":308,"w":180,"h":78,"offX":4,"offY":0,"sourceW":190,"sourceH":82},
"play_red_bot":{"x":1978,"y":54,"w":58,"h":53,"offX":0,"offY":0,"sourceW":58,"sourceH":53},
"play_red_pop":{"x":0,"y":0,"w":286,"h":306,"offX":0,"offY":0,"sourceW":286,"sourceH":306},
"play_redcoin_bg":{"x":1601,"y":386,"w":141,"h":39,"offX":3,"offY":10,"sourceW":153,"sourceH":61},
"play_redn_bg":{"x":529,"y":115,"w":407,"h":83,"offX":0,"offY":0,"sourceW":407,"sourceH":83},
"play_robot":{"x":617,"y":299,"w":91,"h":102,"offX":3,"offY":1,"sourceW":96,"sourceH":103},
"play_robot_eye":{"x":2009,"y":274,"w":32,"h":29,"offX":33,"offY":43,"sourceW":96,"sourceH":103},
"play_rule":{"x":787,"y":394,"w":75,"h":74,"offX":0,"offY":0,"sourceW":75,"sourceH":74},
"play_star_small":{"x":2025,"y":109,"w":19,"h":19,"offX":0,"offY":0,"sourceW":19,"sourceH":19},
"play_word_1":{"x":0,"y":516,"w":73,"h":53,"offX":0,"offY":0,"sourceW":73,"sourceH":53},
"play_word_2":{"x":1376,"y":471,"w":81,"h":53,"offX":0,"offY":0,"sourceW":81,"sourceH":53},
"play_word_3":{"x":435,"y":241,"w":82,"h":53,"offX":0,"offY":0,"sourceW":82,"sourceH":53},
"play_word_4":{"x":1018,"y":399,"w":102,"h":53,"offX":0,"offY":0,"sourceW":102,"sourceH":53},
"play_word_5":{"x":560,"y":403,"w":100,"h":54,"offX":0,"offY":0,"sourceW":100,"sourceH":54},
"play_word_6":{"x":182,"y":308,"w":104,"h":55,"offX":0,"offY":0,"sourceW":104,"sourceH":55},
"play_word_7":{"x":966,"y":0,"w":560,"h":83,"offX":0,"offY":0,"sourceW":560,"sourceH":83},
"double1":{"x":529,"y":200,"w":190,"h":97,"offX":0,"offY":0,"sourceW":190,"sourceH":97},
"double2":{"x":182,"y":369,"w":172,"h":44,"offX":2,"offY":2,"sourceW":176,"sourceH":48},
"doubleFlag":{"x":1403,"y":259,"w":51,"h":29,"offX":2,"offY":1,"sourceW":55,"sourceH":32},
"failDoubleEnd":{"x":1619,"y":522,"w":120,"h":28,"offX":2,"offY":2,"sourceW":124,"sourceH":32},
"failDoublePre1":{"x":348,"y":494,"w":146,"h":27,"offX":2,"offY":2,"sourceW":150,"sourceH":31},
"failDoublePre2":{"x":496,"y":511,"w":146,"h":27,"offX":2,"offY":2,"sourceW":150,"sourceH":31},
"failDoublePre3":{"x":1000,"y":506,"w":146,"h":27,"offX":2,"offY":2,"sourceW":150,"sourceH":31},
"failDoublePre4":{"x":348,"y":523,"w":99,"h":27,"offX":2,"offY":2,"sourceW":103,"sourceH":31},
"noDouble1":{"x":721,"y":200,"w":191,"h":96,"offX":0,"offY":0,"sourceW":191,"sourceH":96},
"noDouble2":{"x":1470,"y":386,"w":129,"h":44,"offX":2,"offY":2,"sourceW":133,"sourceH":48}}}